tiqs/__init__.py
tiqs/tiqs.py
tiqs-0.1.1.dist-info/LICENSE
tiqs-0.1.1.dist-info/METADATA
tiqs-0.1.1.dist-info/WHEEL
tiqs-0.1.1.dist-info/top_level.txt
tiqs-0.1.1.dist-info/RECORD
