Metadata-Version: 2.1
Name: tiqs
Version: 0.1.1
Summary: TIQS: Translational Invariant Quantum Solver
Home-page: https://github.com/fminga/tiqs
Author: Fabrizio Minganti, Nathan Shammah
Author-email: UNKNOWN
License: BSD 3 New
Platform: UNKNOWN
